metia/__init__.py
metia/encoders.py
metia/executables.py
metia/ext_programs.py
metia/formats.py
metia/probe.py
metia/utils.py
metia/writter.py
metia-0.3.5.dist-info/METADATA
metia-0.3.5.dist-info/WHEEL
metia-0.3.5.dist-info/entry_points.txt
metia-0.3.5.dist-info/top_level.txt
metia-0.3.5.dist-info/RECORD
