Metadata-Version: 2.1
Name: metia
Version: 0.3.5
Summary: A tool to parse and extract audio metadata.
Home-page: https://github.com/Davidyz/metia
Author: David Yu
Author-email: hzjlyz@gmail.com
Project-URL: Bug Tracker, https://github.com/Davidyz/metia/issues
Classifier: Programming Language :: Python :: 3
Classifier: License :: OSI Approved :: MIT License
Classifier: Operating System :: POSIX :: Linux
Classifier: Operating System :: MacOS
Classifier: Topic :: Multimedia
Requires-Python: >=3.8
